hestia_earth/__init__.py
hestia_earth/config/Cycle.json
hestia_earth/config/ImpactAssessment.json
hestia_earth/config/Site.json
hestia_earth/config/__init__.py
hestia_earth/config/log.py
hestia_earth/config/run-calculations.json
hestia_earth/config/trigger-calculations.json
hestia_earth/config/utils.py
hestia_earth/config/version.py
tests/integration/__init__.py
tests/integration/test_config.py
tests/integration/test_utils.py
hestia_earth_config-0.65.6.post1.dist-info/LICENSE
hestia_earth_config-0.65.6.post1.dist-info/METADATA
hestia_earth_config-0.65.6.post1.dist-info/WHEEL
hestia_earth_config-0.65.6.post1.dist-info/top_level.txt
hestia_earth_config-0.65.6.post1.dist-info/RECORD
