Metadata-Version: 2.1
Name: hestia-earth-config
Version: 0.65.6.post1
Summary: HESTIA's default engine configuration files.
Home-page: https://gitlab.com/hestia-earth/hestia-engine-config
Author: HESTIA Team
Author-email: guillaume@hestia.earth
License: MIT
Platform: UNKNOWN
Classifier: License :: OSI Approved :: GNU General Public License v3 (GPLv3)
Classifier: Programming Language :: Python :: 3.6
License-File: LICENSE
